adafruit_circuitpython_portalbase-3.5.0.dist-info/licenses/LICENSE
adafruit_portalbase/__init__.py
adafruit_portalbase/graphics.py
adafruit_portalbase/network.py
adafruit_portalbase/wifi_coprocessor.py
adafruit_portalbase/wifi_esp32s2.py
adafruit_circuitpython_portalbase-3.5.0.dist-info/METADATA
adafruit_circuitpython_portalbase-3.5.0.dist-info/WHEEL
adafruit_circuitpython_portalbase-3.5.0.dist-info/top_level.txt
adafruit_circuitpython_portalbase-3.5.0.dist-info/RECORD
