Metadata-Version: 2.4
Name: adafruit-circuitpython-portalbase
Version: 3.5.0
Summary: Base Library for the Portal-style libraries.
Author-email: Adafruit Industries <circuitpython@adafruit.com>
License: MIT
Project-URL: Homepage, https://github.com/adafruit/Adafruit_CircuitPython_PortalBase
Keywords: adafruit,blinka,circuitpython,micropython,portalbase,PyPortal,MatrixPortal,MagTag,Portal,base
Classifier: Intended Audience :: Developers
Classifier: Topic :: Software Development :: Libraries
Classifier: Topic :: Software Development :: Embedded Systems
Classifier: Topic :: System :: Hardware
Classifier: License :: OSI Approved :: MIT License
Classifier: Programming Language :: Python :: 3
License-File: LICENSE
Requires-Dist: Adafruit-Blinka-displayio
Requires-Dist: Adafruit-Blinka
Requires-Dist: adafruit-circuitpython-bitmap-font
Requires-Dist: adafruit-circuitpython-connectionmanager
Requires-Dist: adafruit-circuitpython-display-text
Requires-Dist: adafruit-circuitpython-neopixel
Requires-Dist: adafruit-circuitpython-adafruitio
Requires-Dist: adafruit-circuitpython-miniqr
Requires-Dist: adafruit-circuitpython-requests
Requires-Dist: adafruit-circuitpython-fakerequests
Requires-Dist: adafruit-circuitpython-simpleio
Requires-Dist: adafruit-circuitpython-imageload
Provides-Extra: optional
Requires-Dist: pytest; extra == "optional"
Dynamic: license-file
